pertvi/__init__.py
pertvi/model/__init__.py
pertvi/model/pertvi.py
pertvi/module/__init__.py
pertvi/module/pertvi.py
pertvi-0.0.1.dist-info/METADATA
pertvi-0.0.1.dist-info/WHEEL
pertvi-0.0.1.dist-info/top_level.txt
pertvi-0.0.1.dist-info/RECORD
